jupyterlab_logout/__init__.py
jupyterlab_logout/_version.py
jupyterlab_logout-1.1.0.data/data/share/jupyter/labextensions/jupyterlab-logout/package.json
jupyterlab_logout-1.1.0.data/data/share/jupyter/labextensions/jupyterlab-logout/schemas/jupyterlab-logout/package.json.orig
jupyterlab_logout-1.1.0.data/data/share/jupyter/labextensions/jupyterlab-logout/schemas/jupyterlab-logout/plugin.json
jupyterlab_logout-1.1.0.data/data/share/jupyter/labextensions/jupyterlab-logout/static/883.7d8041b10450a22e2ccd.js
jupyterlab_logout-1.1.0.data/data/share/jupyter/labextensions/jupyterlab-logout/static/remoteEntry.54150020352d9f37bf63.js
jupyterlab_logout-1.1.0.data/data/share/jupyter/labextensions/jupyterlab-logout/static/style.js
jupyterlab_logout-1.1.0.data/data/share/jupyter/labextensions/jupyterlab-logout/static/third-party-licenses.json
jupyterlab_logout-1.1.0.data/data/share/jupyter/labextensions/jupyterlab-logout/install.json
jupyterlab_logout-1.1.0.dist-info/METADATA
jupyterlab_logout-1.1.0.dist-info/WHEEL
jupyterlab_logout-1.1.0.dist-info/licenses/LICENSE
jupyterlab_logout-1.1.0.dist-info/RECORD
